ingestar/__init__.py
ingestar/version.py
ingestar/backend/__init__.py
ingestar/backend/pipeline/__init__.py
ingestar/backend/pipeline/batch_analyze.py
ingestar/backend/pipeline/model_init.py
ingestar/backend/pipeline/model_json_to_middle_json.py
ingestar/backend/pipeline/model_list.py
ingestar/backend/pipeline/para_split.py
ingestar/backend/pipeline/pipeline_analyze.py
ingestar/backend/pipeline/pipeline_magic_model.py
ingestar/backend/pipeline/pipeline_middle_json_mkcontent.py
ingestar/backend/vlm/__init__.py
ingestar/backend/vlm/custom_logits_processors.py
ingestar/backend/vlm/model_output_to_middle_json.py
ingestar/backend/vlm/vlm_analyze.py
ingestar/backend/vlm/vlm_magic_model.py
ingestar/backend/vlm/vlm_middle_json_mkcontent.py
ingestar/cli/__init__.py
ingestar/cli/client.py
ingestar/cli/common.py
ingestar/cli/fast_api.py
ingestar/cli/gradio_app.py
ingestar/cli/models_download.py
ingestar/cli/vlm_vllm_server.py
ingestar/data/__init__.py
ingestar/data/data_reader_writer/__init__.py
ingestar/data/data_reader_writer/base.py
ingestar/data/data_reader_writer/dummy.py
ingestar/data/data_reader_writer/filebase.py
ingestar/data/data_reader_writer/multi_bucket_s3.py
ingestar/data/data_reader_writer/s3.py
ingestar/data/io/__init__.py
ingestar/data/io/base.py
ingestar/data/io/http.py
ingestar/data/io/s3.py
ingestar/data/utils/__init__.py
ingestar/data/utils/exceptions.py
ingestar/data/utils/path_utils.py
ingestar/data/utils/schemas.py
ingestar/libruntime/__init__.py
ingestar/libruntime/pyarmor_runtime.pyd
ingestar/model/__init__.py
ingestar/model/layout/__init__.py
ingestar/model/layout/doclayout_yolo.py
ingestar/model/layout/doclayoutyolo.py
ingestar/model/mfd/__init__.py
ingestar/model/mfd/yolo_v8.py
ingestar/model/mfr/__init__.py
ingestar/model/mfr/unimernet/Unimernet.py
ingestar/model/mfr/unimernet/__init__.py
ingestar/model/mfr/unimernet/unimernet_hf/__init__.py
ingestar/model/mfr/unimernet/unimernet_hf/modeling_unimernet.py
ingestar-0.1.7.dist-info/licenses/LICENSE
ingestar-0.1.7.dist-info/METADATA
ingestar-0.1.7.dist-info/WHEEL
ingestar-0.1.7.dist-info/entry_points.txt
ingestar-0.1.7.dist-info/top_level.txt
ingestar-0.1.7.dist-info/RECORD
